[
    [
        {
            "rule": "10.2.1",
            "sourceId": [
                "10"
            ],
            "conditions": [
                [
                    "事件",
                    "is",
                    "中"
                ],
                [
                    "交易方式",
                    "is",
                    "竞争买卖"
                ],
                [
                    "交易市场",
                    "is",
                    "东京证券交易所"
                ],
                [
                    "交易方向",
                    "is",
                    "买入"
                ],
                [
                    "交易品种",
                    "is",
                    "债券"
                ]
            ],
            "consequences": [
                [
                    "低价的卖价",
                    "优先于",
                    "高价的卖价"
                ],
                [
                    "高价的买价",
                    "优先于",
                    "低价的买价"
                ]
            ]
        }
    ],
    [
        {
            "rule": "10.2.2",
            "sourceId": [
                "10"
            ],
            "conditions": [
                [
                    "事件",
                    "is",
                    "中"
                ],
                [
                    "交易方式",
                    "is",
                    "竞争买卖"
                ],
                [
                    "交易市场",
                    "is",
                    "东京证券交易所"
                ],
                [
                    "交易方向",
                    "is",
                    "卖出"
                ],
                [
                    "交易品种",
                    "is",
                    "债券"
                ]
            ],
            "consequences": [
                [
                    "低价的卖价",
                    "优先于",
                    "高价的卖价"
                ],
                [
                    "高价的买价",
                    "优先于",
                    "低价的买价"
                ]
            ]
        }
    ],
    [
        {
            "rule": "10.3.1",
            "sourceId": [
                "10"
            ],
            "conditions": [
                [
                    "事件",
                    "is",
                    "中"
                ],
                [
                    "交易方式",
                    "is",
                    "竞争买卖"
                ],
                [
                    "交易市场",
                    "is",
                    "东京证券交易所"
                ],
                [
                    "交易方向",
                    "is",
                    "买入"
                ],
                [
                    "交易品种",
                    "is",
                    "债券"
                ]
            ],
            "consequences": [
                [
                    "低价的卖价",
                    "优先于",
                    "高价的卖价"
                ],
                [
                    "高价的买价",
                    "优先于",
                    "低价的买价"
                ],
                [
                    "事件",
                    "is",
                    "中"
                ],
                [
                    "交易方式",
                    "is",
                    "竞争买卖"
                ],
                [
                    "时间",
                    "is",
                    "在进行了呼值的时间的前后"
                ]
            ]
        }
    ],
    [
        {
            "rule": "10.3.2",
            "sourceId": [
                "10"
            ],
            "conditions": [
                [
                    "事件",
                    "is",
                    "中"
                ],
                [
                    "交易方式",
                    "is",
                    "竞争买卖"
                ],
                [
                    "交易市场",
                    "is",
                    "东京证券交易所"
                ],
                [
                    "交易方向",
                    "is",
                    "卖出"
                ],
                [
                    "交易品种",
                    "is",
                    "债券"
                ]
            ],
            "consequences": [
                [
                    "低价的卖价",
                    "优先于",
                    "高价的卖价"
                ],
                [
                    "高价的买价",
                    "优先于",
                    "低价的买价"
                ],
                [
                    "事件",
                    "is",
                    "中"
                ],
                [
                    "交易方式",
                    "is",
                    "竞争买卖"
                ],
                [
                    "时间",
                    "is",
                    "在进行了呼值的时间的前后"
                ]
            ]
        }
    ],
    [
        {
            "rule": "10.4.1",
            "sourceId": [
                "10"
            ],
            "conditions": [
                [
                    "rule",
                    "is",
                    "4"
                ],
                [
                    "交易市场",
                    "is",
                    "东京证券交易所"
                ],
                [
                    "交易方向",
                    "is",
                    "买入"
                ],
                [
                    "交易品种",
                    "is",
                    "债券"
                ]
            ],
            "consequences": [
                [
                    "if",
                    "事件",
                    "is"
                ],
                [
                    "约束",
                    "is",
                    "中"
                ],
                [
                    "交易方式",
                    "is",
                    "竞争买卖"
                ]
            ]
        }
    ],
    [
        {
            "rule": "10.4.2",
            "sourceId": [
                "10"
            ],
            "conditions": [
                [
                    "rule",
                    "is",
                    "4"
                ],
                [
                    "交易市场",
                    "is",
                    "东京证券交易所"
                ],
                [
                    "交易方向",
                    "is",
                    "卖出"
                ],
                [
                    "交易品种",
                    "is",
                    "债券"
                ]
            ],
            "consequences": [
                [
                    "if",
                    "事件",
                    "is"
                ],
                [
                    "约束",
                    "is",
                    "中"
                ],
                [
                    "交易方式",
                    "is",
                    "竞争买卖"
                ]
            ]
        }
    ],
    [
        {
            "rule": "10.5.1",
            "sourceId": [
                "10"
            ],
            "conditions": [
                [
                    "rule",
                    "is",
                    "5"
                ],
                [
                    "交易市场",
                    "is",
                    "东京证券交易所"
                ],
                [
                    "交易方向",
                    "is",
                    "买入"
                ],
                [
                    "交易品种",
                    "is",
                    "债券"
                ]
            ],
            "consequences": [
                [
                    "if",
                    "事件",
                    "is"
                ],
                [
                    "约束",
                    "is",
                    "中"
                ],
                [
                    "交易方式",
                    "is",
                    "竞争买卖"
                ]
            ]
        }
    ],
    [
        {
            "rule": "10.5.2",
            "sourceId": [
                "10"
            ],
            "conditions": [
                [
                    "rule",
                    "is",
                    "5"
                ],
                [
                    "交易市场",
                    "is",
                    "东京证券交易所"
                ],
                [
                    "交易方向",
                    "is",
                    "卖出"
                ],
                [
                    "交易品种",
                    "is",
                    "债券"
                ]
            ],
            "consequences": [
                [
                    "if",
                    "事件",
                    "is"
                ],
                [
                    "约束",
                    "is",
                    "中"
                ],
                [
                    "交易方式",
                    "is",
                    "竞争买卖"
                ]
            ]
        }
    ],
    [
        {
            "rule": "14.1",
            "sourceId": [
                "14"
            ],
            "conditions": [
                [
                    "操作",
                    "is",
                    "认购"
                ],
                [
                    "债券",
                    "is",
                    "各债券的金额（以下简称“面值”）"
                ],
                [
                    "单位",
                    "is",
                    "每100日元1分钱"
                ],
                [
                    "交易品种",
                    "is",
                    "可转换公司债券型新股认购权公司债券及可交换公司债券"
                ],
                [
                    "交易市场",
                    "is",
                    "东京证券交易所"
                ],
                [
                    "交易方向",
                    "is",
                    "买入"
                ]
            ],
            "consequences": [
                [
                    "面值",
                    "is",
                    "每100日元5分钱"
                ]
            ]
        }
    ],
    [
        {
            "rule": "14.2",
            "sourceId": [
                "14"
            ],
            "conditions": [
                [
                    "操作",
                    "is",
                    "认购"
                ],
                [
                    "债券",
                    "is",
                    "各债券的金额（以下简称“面值”）"
                ],
                [
                    "单位",
                    "is",
                    "每100日元1分钱"
                ],
                [
                    "交易品种",
                    "is",
                    "债券"
                ],
                [
                    "交易品种",
                    "is",
                    "可转换公司债券型新股认购权公司债券及可交换公司债券"
                ],
                [
                    "交易市场",
                    "is",
                    "东京证券交易所"
                ],
                [
                    "交易方向",
                    "is",
                    "买入"
                ]
            ],
            "consequences": [
                [
                    "面值",
                    "is",
                    "每100日元5分钱"
                ],
                [
                    "呼值",
                    "不能",
                    "取得"
                ],
                [
                    "价格幅度",
                    "is",
                    "不超过本交易所根据规则规定的价宽限度的价格"
                ],
                [
                    "交易品种",
                    "is",
                    "债券"
                ],
                [
                    "交易品种",
                    "is",
                    "可转换公司债券型新股认购权公司债券及可交换公司债券"
                ],
                [
                    "交易品种",
                    "is",
                    "可转换公司债券型新股认购权公司债券及可交换"
                ]
            ]
        }
    ],
    [
        {
            "rule": "15.1.1",
            "sourceId": [
                "15"
            ],
            "conditions": [
                [
                    "交易品种",
                    "is",
                    "债券"
                ],
                [
                    "交易品种",
                    "is",
                    "国债证券"
                ],
                [
                    "交易市场",
                    "is",
                    "东京证券交易所"
                ],
                [
                    "交易方向",
                    "is",
                    "买入"
                ]
            ],
            "consequences": [
                [
                    "面值",
                    "is",
                    "1000万日元"
                ],
                [
                    "操作",
                    "is",
                    "根据"
                ],
                [
                    "操作部分",
                    "is",
                    "本交易所规定"
                ]
            ]
        }
    ],
    [
        {
            "rule": "15.1.2",
            "sourceId": [
                "15"
            ],
            "conditions": [
                [
                    "交易品种",
                    "is",
                    "债券"
                ],
                [
                    "交易品种",
                    "is",
                    "国债证券"
                ],
                [
                    "交易市场",
                    "is",
                    "东京证券交易所"
                ],
                [
                    "交易方向",
                    "is",
                    "卖出"
                ]
            ],
            "consequences": [
                [
                    "面值",
                    "is",
                    "1000万日元"
                ],
                [
                    "操作",
                    "is",
                    "根据"
                ],
                [
                    "操作部分",
                    "is",
                    "本交易所规定"
                ]
            ]
        }
    ],
    [
        {
            "rule": "15.2.1",
            "sourceId": [
                "15"
            ],
            "conditions": [
                [
                    "交易品种",
                    "is",
                    "债券"
                ],
                [
                    "交易品种",
                    "is",
                    "国债证券"
                ],
                [
                    "交易市场",
                    "is",
                    "东京证券交易所"
                ],
                [
                    "交易方向",
                    "is",
                    "买入"
                ]
            ],
            "consequences": [
                [
                    "面值",
                    "is",
                    "100万日元"
                ],
                [
                    "操作",
                    "is",
                    "根据"
                ],
                [
                    "操作部分",
                    "is",
                    "本交易所规定"
                ]
            ]
        }
    ],
    [
        {
            "rule": "15.2.2",
            "sourceId": [
                "15"
            ],
            "conditions": [
                [
                    "交易品种",
                    "is",
                    "债券"
                ],
                [
                    "交易品种",
                    "is",
                    "国债证券"
                ],
                [
                    "交易市场",
                    "is",
                    "东京证券交易所"
                ],
                [
                    "交易方向",
                    "is",
                    "卖出"
                ]
            ],
            "consequences": [
                [
                    "面值",
                    "is",
                    "100万日元"
                ],
                [
                    "操作",
                    "is",
                    "根据"
                ],
                [
                    "操作部分",
                    "is",
                    "本交易所规定"
                ]
            ]
        }
    ],
    [
        {
            "rule": "15.3.1",
            "sourceId": [
                "15"
            ],
            "conditions": [
                [
                    "交易品种",
                    "is",
                    "债券"
                ],
                [
                    "交易品种",
                    "is",
                    "国债证券"
                ],
                [
                    "交易市场",
                    "is",
                    "东京证券交易所"
                ],
                [
                    "交易方向",
                    "is",
                    "买入"
                ]
            ],
            "consequences": [
                [
                    "面值",
                    "is",
                    "10万日元"
                ],
                [
                    "操作",
                    "is",
                    "根据"
                ],
                [
                    "操作部分",
                    "is",
                    "本交易所规定"
                ]
            ]
        }
    ],
    [
        {
            "rule": "15.3.2",
            "sourceId": [
                "15"
            ],
            "conditions": [
                [
                    "交易品种",
                    "is",
                    "债券"
                ],
                [
                    "交易品种",
                    "is",
                    "国债证券"
                ],
                [
                    "交易市场",
                    "is",
                    "东京证券交易所"
                ],
                [
                    "交易方向",
                    "is",
                    "卖出"
                ]
            ],
            "consequences": [
                [
                    "面值",
                    "is",
                    "10万日元"
                ],
                [
                    "操作",
                    "is",
                    "根据"
                ],
                [
                    "操作部分",
                    "is",
                    "本交易所规定"
                ]
            ]
        }
    ],
    [
        {
            "rule": "15.4.1",
            "sourceId": [
                "15"
            ],
            "conditions": [
                [
                    "交易品种",
                    "is",
                    "债券"
                ],
                [
                    "交易品种",
                    "is",
                    "国债证券"
                ],
                [
                    "交易市场",
                    "is",
                    "东京证券交易所"
                ],
                [
                    "交易方向",
                    "is",
                    "买入"
                ]
            ],
            "consequences": [
                [
                    "面值",
                    "is",
                    "5万日元"
                ],
                [
                    "操作",
                    "is",
                    "根据"
                ],
                [
                    "操作部分",
                    "is",
                    "本交易所规定"
                ]
            ]
        }
    ],
    [
        {
            "rule": "15.4.2",
            "sourceId": [
                "15"
            ],
            "conditions": [
                [
                    "交易品种",
                    "is",
                    "债券"
                ],
                [
                    "交易品种",
                    "is",
                    "国债证券"
                ],
                [
                    "交易市场",
                    "is",
                    "东京证券交易所"
                ],
                [
                    "交易方向",
                    "is",
                    "卖出"
                ]
            ],
            "consequences": [
                [
                    "面值",
                    "is",
                    "5万日元"
                ],
                [
                    "操作",
                    "is",
                    "根据"
                ],
                [
                    "操作部分",
                    "is",
                    "本交易所规定"
                ]
            ]
        }
    ]
]